seealgo/__init__.py
seealgo/see_dict_algo.py
seealgo/see_list_algo.py
seealgo/see_set_algo.py
seealgo/see_tree_algo.py
seealgo/tests/__init__.py
seealgo/tests/test_dict.py
seealgo/tests/test_list.py
seealgo/tests/test_set.py
seealgo/tests/test_tree.py
seealgo-0.2.0.dist-info/LICENSE
seealgo-0.2.0.dist-info/METADATA
seealgo-0.2.0.dist-info/WHEEL
seealgo-0.2.0.dist-info/top_level.txt
seealgo-0.2.0.dist-info/RECORD
