Metadata-Version: 2.1
Name: seealgo
Version: 0.2.0
Summary: A Python library to visualize a data structure as it changes throughout a function
Author-email: Sarah Tang <sarah.tang@columbia.edu>
Requires-Python: >=3.7
License-File: LICENSE
Requires-Dist: graphviz
